{"Vocabulary": {"back": 79, "to": 888, "german": 348, "has": 381, "in": 423, "after": 17, "huge": 412, "report": 721, "the": 865, "announced": 47, "net": 583, "of": 602, "compared": 180, "with": 976, "were": 959, "at": 67, "times": 886, "more": 563, "than": 860, "was": 948, "hit": 400, "by": 125, "competition": 182, "and": 46, "demand": 219, "following": 324, "war": 945, "it": 449, "also": 34, "its": 450, "us": 925, "business": 122, "last": 475, "year": 991, "even": 285, "as": 64, "some": 801, "european": 284, "on": 613, "per": 646, "share": 777, "did": 229, "not": 594, "get": 352, "company": 179, "said": 745, "that": 863, "will": 973, "give": 354, "all": 27, "details": 225, "results": 729, "march": 525, "files": 310, "for": 327, "group": 373, "market": 527, "once": 614, "among": 40, "most": 564, "would": 987, "open": 618, "but": 123, "analysts": 44, "likely": 499, "number": 599, "sites": 792, "firm": 316, "total": 901, "bn": 109, "biggest": 103, "foods": 326, "which": 966, "say": 751, "had": 377, "up": 924, "consumers": 187, "been": 92, "need": 580, "month": 560, "plan": 655, "earlier": 259, "this": 878, "into": 444, "expected": 294, "new": 587, "chief": 155, "executive": 293, "use": 926, "space": 809, "take": 846, "action": 7, "turn": 912, "itself": 451, "around": 61, "includes": 427, "significant": 786, "cost": 192, "service": 773, "he": 384, "yet": 994, "mr": 567, "job": 457, "be": 88, "put": 698, "off": 603, "customers": 206, "real": 709, "big": 102, "issue": 447, "is": 446, "going": 358, "over": 628, "next": 590, "one": 615, "or": 620, "two": 915, "now": 598, "they": 873, "are": 56, "their": 866, "see": 765, "local": 504, "economy": 265, "still": 827, "growing": 375, "says": 753, "areas": 58, "saw": 750, "continue": 190, "december": 216, "early": 260, "january": 454, "latest": 478, "book": 111, "study": 833, "economic": 264, "growth": 376, "only": 617, "area": 57, "behind": 95, "consumer": 186, "spending": 814, "higher": 396, "november": 597, "sales": 746, "labour": 472, "several": 776, "reported": 722, "prices": 680, "building": 120, "overall": 629, "price": 679, "levels": 494, "added": 11, "strong": 831, "commercial": 174, "office": 606, "washington": 949, "york": 995, "city": 161, "nations": 576, "build": 119, "general": 347, "worlds": 986, "show": 782, "compete": 181, "europe": 283, "president": 675, "part": 634, "efforts": 271, "make": 520, "first": 318, "should": 781, "go": 357, "way": 951, "centre": 145, "about": 1, "operations": 619, "groups": 374, "may": 530, "workers": 982, "germany": 350, "have": 382, "face": 296, "seen": 767, "good": 360, "news": 588, "since": 788, "years": 993, "leaders": 484, "do": 241, "plans": 657, "american": 38, "an": 42, "long": 506, "could": 194, "from": 339, "other": 624, "success": 835, "without": 978, "there": 870, "production": 688, "help": 390, "currently": 205, "half": 378, "what": 962, "major": 519, "numbers": 600, "money": 559, "previous": 678, "uk": 917, "same": 748, "different": 233, "another": 49, "further": 343, "reduce": 716, "where": 964, "doing": 246, "so": 796, "remove": 720, "dollar": 247, "making": 522, "everyone": 289, "industry": 434, "best": 99, "forward": 333, "we": 952, "know": 469, "five": 319, "today": 890, "leading": 485, "told": 892, "bbc": 86, "current": 204, "allow": 30, "chance": 150, "test": 857, "drive": 253, "fleet": 320, "across": 5, "countries": 196, "potential": 671, "try": 909, "out": 627, "hours": 407, "similar": 787, "wanted": 944, "change": 152, "them": 867, "recent": 712, "bank": 82, "no": 592, "rate": 704, "decision": 218, "keep": 463, "interest": 440, "rates": 705, "hold": 403, "body": 110, "minutes": 553, "member": 541, "policy": 664, "committee": 175, "paul": 641, "who": 969, "released": 719, "week": 955, "main": 518, "might": 547, "fall": 299, "however": 411, "point": 661, "rise": 734, "meeting": 540, "members": 542, "increase": 429, "due": 256, "course": 198, "if": 416, "line": 500, "central": 144, "vote": 942, "made": 517, "soon": 804, "trying": 910, "focus": 323, "then": 869, "probably": 682, "any": 51, "until": 923, "later": 477, "look": 508, "before": 93, "hope": 406, "japan": 455, "japanese": 456, "time": 885, "sent": 769, "high": 395, "three": 882, "april": 55, "day": 211, "points": 662, "against": 19, "helped": 391, "final": 313, "months": 561, "performance": 648, "whole": 970, "figures": 308, "brought": 117, "response": 727, "low": 513, "risk": 735, "serious": 772, "despite": 224, "such": 836, "within": 977, "key": 466, "better": 100, "products": 689, "during": 257, "charges": 154, "close": 166, "former": 332, "court": 199, "him": 397, "trial": 906, "june": 461, "case": 138, "being": 96, "political": 665, "his": 398, "legal": 490, "include": 425, "tax": 849, "my": 572, "file": 309, "me": 532, "each": 258, "possible": 669, "few": 304, "days": 212, "began": 94, "running": 742, "work": 981, "russian": 744, "bill": 104, "effort": 270, "win": 974, "china": 157, "down": 251, "state": 823, "media": 536, "lead": 482, "too": 894, "much": 569, "system": 844, "above": 2, "means": 534, "energy": 279, "world": 985, "oil": 609, "government": 364, "does": 244, "mean": 533, "hard": 380, "seems": 766, "chinese": 158, "thus": 884, "far": 300, "international": 442, "pressure": 677, "least": 487, "level": 493, "taking": 848, "effect": 267, "october": 601, "february": 301, "although": 35, "won": 980, "battle": 85, "phone": 652, "reports": 723, "firms": 317, "deal": 214, "according": 4, "thought": 881, "having": 383, "under": 919, "name": 573, "lost": 511, "when": 963, "while": 967, "jobs": 458, "come": 169, "street": 830, "past": 639, "companies": 178, "cut": 207, "costs": 193, "between": 101, "buy": 124, "either": 275, "access": 3, "global": 356, "network": 584, "own": 630, "mobile": 556, "both": 112, "project": 693, "provide": 695, "paper": 633, "house": 408, "second": 761, "always": 36, "department": 220, "de": 213, "spokesman": 815, "whether": 965, "election": 276, "west": 960, "london": 505, "via": 936, "support": 840, "how": 409, "small": 795, "survey": 843, "found": 334, "many": 524, "training": 904, "looking": 509, "council": 195, "needs": 582, "period": 649, "failed": 298, "volume": 941, "ahead": 22, "stock": 828, "move": 565, "winning": 975, "used": 927, "record": 714, "working": 983, "late": 476, "september": 770, "just": 462, "short": 780, "well": 957, "mark": 526, "result": 728, "rather": 706, "ever": 287, "third": 877, "became": 89, "personal": 651, "olympics": 612, "light": 497, "find": 315, "difficult": 234, "taxes": 850, "public": 696, "western": 961, "warned": 947, "increased": 430, "russia": 743, "future": 344, "ago": 21, "foreign": 330, "impact": 421, "spend": 813, "thanks": 861, "social": 797, "trade": 903, "those": 879, "party": 638, "lot": 512, "done": 248, "came": 129, "must": 571, "rule": 739, "law": 481, "meet": 539, "finally": 314, "become": 91, "reached": 707, "date": 209, "can": 131, "terms": 856, "side": 785, "included": 426, "life": 496, "issues": 448, "data": 208, "standard": 819, "almost": 31, "less": 491, "people": 644, "weeks": 956, "like": 498, "egypt": 272, "amount": 41, "south": 807, "end": 278, "instead": 438, "british": 116, "through": 883, "start": 821, "something": 803, "recently": 713, "fact": 297, "problems": 685, "again": 18, "already": 33, "tuesday": 911, "middle": 546, "east": 262, "together": 891, "series": 771, "projects": 694, "led": 488, "minister": 552, "eastern": 263, "sea": 758, "particularly": 636, "our": 626, "situation": 793, "saying": 752, "interested": 441, "national": 575, "problem": 684, "needed": 581, "security": 764, "decided": 217, "grant": 366, "involved": 445, "pay": 642, "french": 338, "official": 607, "staff": 817, "france": 336, "eu": 282, "home": 405, "popular": 666, "want": 943, "grand": 365, "built": 121, "created": 201, "miles": 548, "power": 672, "these": 872, "director": 236, "because": 90, "able": 0, "you": 996, "union": 920, "though": 880, "enough": 280, "why": 972, "here": 393, "great": 369, "university": 922, "region": 717, "dont": 249, "designed": 223, "old": 610, "britain": 114, "bad": 80, "doesnt": 245, "never": 586, "near": 578, "things": 875, "makes": 521, "phones": 653, "started": 822, "four": 335, "nearly": 579, "institute": 439, "set": 775, "process": 686, "away": 78, "ms": 568, "research": 724, "very": 935, "head": 385, "force": 328, "lower": 514, "clear": 164, "longer": 507, "certain": 147, "cannot": 133, "quite": 701, "strategy": 829, "believe": 97, "received": 711, "statement": 824, "green": 371, "press": 676, "release": 718, "evidence": 290, "services": 774, "taken": 847, "control": 191, "six": 794, "post": 670, "speed": 812, "role": 737, "launched": 480, "known": 470, "took": 895, "death": 215, "states": 825, "claims": 163, "order": 622, "track": 902, "call": 127, "question": 699, "young": 997, "chancellor": 151, "gordon": 362, "rules": 740, "anything": 53, "product": 687, "forces": 329, "stage": 818, "asked": 65, "your": 998, "right": 732, "internet": 443, "top": 898, "users": 929, "getting": 353, "seconds": 762, "music": 570, "comes": 171, "every": 288, "idea": 415, "available": 75, "society": 798, "she": 778, "systems": 845, "using": 930, "development": 228, "person": 650, "africa": 16, "based": 83, "north": 593, "developing": 227, "place": 654, "offer": 605, "drug": 254, "germanys": 351, "create": 200, "drugs": 255, "researchers": 725, "thing": 874, "associated": 66, "advance": 14, "held": 389, "themselves": 868, "million": 551, "package": 631, "launch": 479, "season": 760, "care": 136, "page": 632, "secretary": 763, "called": 128, "country": 197, "women": 979, "whose": 971, "blood": 108, "type": 916, "health": 386, "cases": 139, "example": 292, "movement": 566, "little": 502, "effective": 268, "large": 474, "others": 625, "add": 10, "history": 399, "technical": 853, "single": 789, "champion": 148, "source": 805, "ships": 779, "got": 363, "common": 176, "wrote": 990, "note": 595, "works": 984, "given": 355, "david": 210, "leader": 483, "important": 422, "treatment": 905, "clinical": 165, "cancer": 132, "model": 557, "coming": 172, "material": 529, "cause": 140, "addition": 12, "including": 428, "view": 939, "specific": 811, "died": 231, "information": 437, "analysis": 43, "algeria": 25, "think": 876, "left": 489, "john": 459, "nothing": 596, "red": 715, "present": 674, "august": 74, "germans": 349, "television": 855, "turned": 913, "sources": 806, "special": 810, "card": 135, "july": 460, "community": 177, "parties": 637, "list": 501, "independent": 431, "networks": 585, "her": 392, "tv": 914, "basic": 84, "run": 741, "schools": 755, "military": 549, "resources": 726, "act": 6, "actually": 9, "technology": 854, "live": 503, "effects": 269, "eight": 274, "went": 958, "yearold": 992, "men": 543, "americans": 39, "food": 325, "diet": 232, "game": 345, "population": 667, "century": 146, "double": 250, "version": 934, "really": 710, "thats": 864, "subject": 834, "children": 156, "let": 492, "michael": 544, "meanwhile": 535, "human": 413, "united": 921, "kingdom": 468, "van": 931, "probe": 683, "play": 658, "believed": 98, "bit": 105, "attack": 71, "attacks": 72, "summer": 838, "caused": 141, "robert": 736, "sir": 790, "am": 37, "published": 697, "website": 954, "victory": 937, "position": 668, "described": 221, "true": 908, "brown": 118, "tony": 893, "return": 730, "developed": 226, "cant": 134, "heart": 387, "programme": 691, "particular": 635, "someone": 802, "actor": 8, "la": 471, "various": 932, "conference": 184, "considered": 185, "school": 754, "man": 523, "team": 851, "olympic": 611, "games": 346, "ii": 417, "didnt": 230, "white": 968, "divisions": 240, "award": 76, "title": 887, "sugar": 837, "britains": 115, "career": 137, "original": 623, "offensive": 604, "full": 342, "shows": 783, "along": 32, "feel": 302, "milk": 550, "dr": 252, "pepper": 645, "online": 616, "surface": 842, "often": 608, "review": 731, "campaign": 130, "prime": 681, "peace": 643, "race": 702, "sure": 841, "choice": 160, "fight": 306, "james": 453, "earth": 261, "im": 418, "digital": 235, "played": 659, "software": 799, "air": 24, "indoor": 433, "search": 759, "modern": 558, "films": 312, "film": 311, "festival": 303, "mission": 554, "box": 113, "station": 826, "experience": 295, "individual": 432, "star": 820, "channel": 153, "form": 331, "theres": 871, "rights": 733, "comedy": 170, "email": 277, "kennedy": 464, "age": 20, "night": 591, "youre": 999, "radio": 703, "attempt": 73, "send": 768, "site": 791, "th": 859, "awards": 77, "ive": 452, "content": 189, "event": 286, "front": 340, "learn": 486, "holmes": 404, "gold": 359, "writing": 989, "black": 106, "howard": 410, "code": 167, "sport": 816, "science": 756, "anyone": 52, "medical": 537, "screen": 757, "police": 663, "doctors": 243, "art": 62, "read": 708, "ground": 372, "design": 222, "sun": 839, "image": 419, "video": 938, "chocolate": 159, "water": 950, "blair": 107, "web": 953, "free": 337, "writes": 988, "doctor": 242, "hand": 379, "land": 473, "education": 266, "lord": 510, "ancient": 45, "hitler": 401, "liberal": 495, "article": 63, "aids": 23, "field": 305, "advanced": 15, "contact": 188, "soldiers": 800, "disease": 237, "answer": 50, "questions": 700, "flight": 321, "salt": 747, "heat": 388, "baking": 81, "cup": 202, "cups": 203, "teaspoon": 852, "color": 168, "vegetables": 933, "md": 531, "center": 142, "please": 660, "etc": 281, "greek": 370, "centers": 143, "ca": 126, "athletes": 69, "percent": 647, "address": 13, "apple": 54, "display": 239, "diseases": 238, "studies": 832, "patients": 640, "programs": 692, "medicine": 538, "program": 690, "images": 420, "tests": 858, "naval": 577, "warfare": 946, "graphics": 368, "computer": 183, "inc": 424, "info": 436, "graphic": 367, "tools": 897, "ftp": 341, "visual": 940, "roman": 738, "user": 928, "tool": 896, "machine": 516, "microsoft": 545, "command": 173, "army": 60, "anonymous": 48, "nasa": 574, "missions": 555, "mars": 528, "planetary": 656, "bc": 87, "shuttle": 784, "satellite": 749, "athens": 68, "egyptian": 273, "examination": 291, "troops": 907, "allies": 29, "allied": 28, "soviet": 808, "armies": 59, "civil": 162, "fighting": 307, "powers": 673, "algerian": 26, "orbit": 621, "fln": 322, "moon": 562, "infection": 435, "hiv": 402, "hicnet": 394, "newsletter": 589, "tobacco": 889, "tories": 899, "kilroysilk": 467, "ukip": 918, "tory": 900, "lunar": 515, "championships": 149, "athletics": 70, "kenteris": 465, "thanou": 862, "iaaf": 414, "google": 361}, "IDF": [3.249303726381109, 1.837396789404492, 3.9614991019117487, 3.9809171877688505, 3.1591526293868113, 3.4819260216498624, 4.084101424004081, 3.5307161858192946, 4.386382295877015, 3.7856084354480846, 3.4583955242396685, 2.971100397883872, 4.084101424004081, 4.000719815065031, 4.084101424004081, 4.511545438831021, 4.357394759003762, 2.001946176452649, 3.424106450761036, 2.753687521278647, 4.329223882037066, 3.636076701477121, 3.801868956319865, 5.022371062597012, 4.301824907848951, 4.917010546939185, 5.07952947643696, 1.9063896608914435, 4.416235259026696, 4.27515666076679, 3.801868956319865, 3.3801433273399204, 3.7538597371335043, 3.0000879347571243, 1.7203803310183041, 3.2780138322635404, 3.622283379344785, 3.1336193273816466, 3.3909542434441358, 4.693866995624976, 3.3801433273399204, 4.041541809585285, 1.581240970599485, 4.5454469905067025, 4.128553186574915, 4.580538310317973, 1.0385443250398818, 3.6786363158959166, 5.427836170705175, 3.092461254888139, 4.175073202209807, 2.292341954776026, 3.4468347018385925, 3.905409635260705, 4.868220382769753, 3.6086777272890065, 1.5462723727617385, 3.7538597371335043, 3.9237587739289017, 4.73468899014523, 3.869691552658626, 2.908796514547717, 4.5454469905067025, 2.9782688873624847, 1.432698258566523, 3.9237587739289017, 4.301824907848951, 1.4144606710167422, 4.175073202209807, 4.357394759003762, 4.27515666076679, 3.905409635260705, 4.175073202209807, 4.084101424004081, 3.738355550597539, 3.2587824703356527, 4.329223882037066, 4.511545438831021, 3.4583955242396685, 2.771079263990516, 3.8183982582710754, 4.968303841326735, 4.02092252238255, 3.5432949680261547, 4.44700691769345, 3.869691552658626, 3.3483946290253397, 5.347793463031639, 1.3460703906899352, 3.887391129758027, 2.5236710906766753, 3.23991398603127, 1.7771779294114372, 2.5328454669527165, 3.6500629434518608, 3.6642475784438173, 2.4877928030117733, 3.3588659288926355, 4.106080330722856, 2.985489135335971, 3.2306115933689563, 2.6604693924465463, 3.4819260216498624, 3.622283379344785, 4.084101424004081, 3.801868956319865, 4.329223882037066, 4.175073202209807, 4.128553186574915, 3.738355550597539, 3.7538597371335043, 4.175073202209807, 2.6816342036385894, 4.106080330722856, 3.3277753418226044, 3.9614991019117487, 2.9223102337144398, 3.9809171877688505, 4.151542704799613, 4.128553186574915, 4.2238633663792395, 4.24918117436353, 3.401883313976326, 1.4830233424540389, 4.128553186574915, 1.4084546469565304, 4.693866995624976, 3.7538597371335043, 3.1420581960275116, 3.249303726381109, 3.801868956319865, 1.9831536771032816, 4.654646282471694, 4.106080330722856, 3.7230880784667506, 4.777248604564027, 4.2238633663792395, 4.2238633663792395, 3.412933150162911, 4.106080330722856, 4.151542704799613, 4.084101424004081, 3.9424509069410543, 4.968303841326735, 3.887391129758027, 4.106080330722856, 4.27515666076679, 4.000719815065031, 3.905409635260705, 4.199170753788868, 3.887391129758027, 4.44700691769345, 3.4819260216498624, 4.357394759003762, 4.511545438831021, 3.2780138322635404, 4.329223882037066, 4.47875561600803, 5.07952947643696, 5.273685490877917, 4.2238633663792395, 3.869691552658626, 4.44700691769345, 3.9424509069410543, 3.582009480206845, 5.204692619390966, 3.6932351153170693, 4.151542704799613, 4.511545438831021, 3.23991398603127, 4.511545438831021, 3.801868956319865, 4.041541809585285, 4.329223882037066, 4.151542704799613, 4.24918117436353, 3.905409635260705, 4.128553186574915, 3.636076701477121, 3.307572634505085, 4.062595218783118, 4.2238633663792395, 4.106080330722856, 3.738355550597539, 4.106080330722856, 4.199170753788868, 4.416235259026696, 4.357394759003762, 4.128553186574915, 4.47875561600803, 3.636076701477121, 3.622283379344785, 3.5307161858192946, 3.9809171877688505, 2.2359890182248945, 4.416235259026696, 3.8522998099467567, 3.3483946290253397, 3.582009480206845, 4.151542704799613, 3.70805020110221, 3.8522998099467567, 4.000719815065031, 4.47875561600803, 3.518293665820737, 3.6642475784438173, 4.357394759003762, 3.424106450761036, 3.4700915640028596, 3.568937398639492, 3.4468347018385925, 3.116952274896435, 3.249303726381109, 4.301824907848951, 3.8522998099467567, 4.084101424004081, 3.5560339938035845, 3.9424509069410543, 3.6086777272890065, 4.02092252238255, 4.041541809585285, 4.041541809585285, 3.7696080941016437, 4.2238633663792395, 3.412933150162911, 4.199170753788868, 3.801868956319865, 4.301824907848951, 3.7696080941016437, 2.8888622996469, 3.9237587739289017, 4.199170753788868, 4.357394759003762, 3.3277753418226044, 3.9424509069410543, 3.8522998099467567, 3.3694480382231724, 3.738355550597539, 4.73468899014523, 4.580538310317973, 4.82170036713486, 2.33679371734686, 4.357394759003762, 4.47875561600803, 3.0000879347571243, 3.9809171877688505, 3.6500629434518608, 4.511545438831021, 3.6086777272890065, 2.8501477874662093, 3.9809171877688505, 2.915530546729061, 4.062595218783118, 4.041541809585285, 4.654646282471694, 4.000719815065031, 3.3588659288926355, 2.831338455508713, 3.167810692129926, 3.43540600601497, 3.1591526293868113, 4.106080330722856, 3.801868956319865, 4.24918117436353, 3.7538597371335043, 3.9614991019117487, 4.511545438831021, 3.738355550597539, 4.151542704799613, 4.128553186574915, 4.128553186574915, 4.084101424004081, 4.868220382769753, 5.022371062597012, 4.000719815065031, 3.622283379344785, 3.905409635260705, 3.622283379344785, 2.7479568465696618, 4.693866995624976, 3.4819260216498624, 4.175073202209807, 5.427836170705175, 3.506023573228923, 3.1005584651207587, 2.71424578922735, 3.9614991019117487, 3.636076701477121, 3.167810692129926, 4.041541809585285, 3.869691552658626, 5.514847547694806, 3.9614991019117487, 3.9614991019117487, 3.1420581960275116, 3.835205376587457, 3.6500629434518608, 3.506023573228923, 4.041541809585285, 3.7538597371335043, 3.1765443720986806, 3.4819260216498624, 4.041541809585285, 4.73468899014523, 3.0375454972920246, 3.7538597371335043, 4.151542704799613, 4.27515666076679, 3.887391129758027, 4.5454469905067025, 4.616905954488847, 3.568937398639492, 4.175073202209807, 3.4583955242396685, 4.084101424004081, 3.1336193273816466, 3.6642475784438173, 4.128553186574915, 2.166539629953023, 3.185355001780836, 5.204692619390966, 4.616905954488847, 5.427836170705175, 4.041541809585285, 3.2306115933689563, 3.6786363158959166, 4.386382295877015, 1.1477038437126343, 3.6086777272890065, 3.8183982582710754, 3.9424509069410543, 3.636076701477121, 3.4468347018385925, 3.9424509069410543, 3.0000879347571243, 3.12525107771113, 3.738355550597539, 3.801868956319865, 3.70805020110221, 1.4814117385596974, 3.9237587739289017, 5.07952947643696, 3.7230880784667506, 3.2683519213518033, 3.506023573228923, 4.616905954488847, 3.9809171877688505, 3.0223936922714225, 3.738355550597539, 4.654646282471694, 3.801868956319865, 4.5454469905067025, 2.5236710906766753, 3.801868956319865, 3.3483946290253397, 3.2213949382640323, 4.062595218783118, 2.992761894665051, 3.060712556573559, 4.02092252238255, 2.8067973465925955, 5.07952947643696, 4.128553186574915, 3.43540600601497, 2.8693177035739295, 4.357394759003762, 4.968303841326735, 4.47875561600803, 4.24918117436353, 2.915530546729061, 4.580538310317973, 4.106080330722856, 4.02092252238255, 3.287770007208905, 4.084101424004081, 4.106080330722856, 3.6786363158959166, 1.8796565986943747, 3.4819260216498624, 4.02092252238255, 3.9614991019117487, 1.5741487422899931, 1.432698258566523, 3.401883313976326, 1.9725715677727447, 3.7538597371335043, 3.5432949680261547, 4.084101424004081, 4.24918117436353, 3.5560339938035845, 2.8888622996469, 4.062595218783118, 3.1942439491980816, 3.401883313976326, 5.966832671437863, 2.8757902180795467, 3.6786363158959166, 3.3483946290253397, 2.2190106816904764, 3.738355550597539, 3.622283379344785, 5.514847547694806, 5.83330127881334, 3.9424509069410543, 4.917010546939185, 3.23991398603127, 3.887391129758027, 3.9424509069410543, 3.9809171877688505, 2.432103897151185, 4.47875561600803, 2.7828441055701028, 3.9809171877688505, 3.8522998099467567, 4.868220382769753, 3.738355550597539, 1.835100577144142, 4.02092252238255, 3.287770007208905, 3.905409635260705, 3.9424509069410543, 4.199170753788868, 3.116952274896435, 1.0426894086950507, 4.868220382769753, 3.3801433273399204, 3.9237587739289017, 4.44700691769345, 2.9223102337144398, 3.622283379344785, 4.301824907848951, 4.000719815065031, 4.151542704799613, 4.27515666076679, 3.801868956319865, 5.347793463031639, 4.73468899014523, 3.116952274896435, 3.518293665820737, 4.44700691769345, 3.6932351153170693, 4.24918117436353, 3.3380318419897934, 3.6642475784438173, 2.1076078515766876, 3.7696080941016437, 1.2256342126266615, 3.6786363158959166, 3.738355550597539, 1.3155971186065245, 1.6783320947748046, 3.8522998099467567, 3.9614991019117487, 4.106080330722856, 3.5560339938035845, 4.175073202209807, 4.329223882037066, 3.869691552658626, 4.44700691769345, 3.5307161858192946, 4.175073202209807, 4.041541809585285, 2.383313732981753, 3.5432949680261547, 4.693866995624976, 5.07952947643696, 3.7230880784667506, 6.120983351265121, 4.82170036713486, 2.8128763926689775, 3.3483946290253397, 4.777248604564027, 3.835205376587457, 4.301824907848951, 3.23991398603127, 2.3217558399823197, 3.6642475784438173, 3.12525107771113, 3.905409635260705, 3.8183982582710754, 3.869691552658626, 4.062595218783118, 3.9809171877688505, 3.835205376587457, 4.199170753788868, 3.7696080941016437, 4.106080330722856, 3.3176229703585864, 3.5560339938035845, 3.506023573228923, 4.199170753788868, 3.2587824703356527, 3.8183982582710754, 3.7538597371335043, 3.738355550597539, 4.24918117436353, 3.3694480382231724, 4.106080330722856, 2.4074112845608133, 3.3801433273399204, 3.6500629434518608, 3.7538597371335043, 3.412933150162911, 3.869691552658626, 3.738355550597539, 3.43540600601497, 2.971100397883872, 3.9809171877688505, 3.2213949382640323, 3.493902212696578, 4.386382295877015, 3.622283379344785, 3.5307161858192946, 3.5952547069568657, 3.738355550597539, 4.777248604564027, 4.416235259026696, 2.4703251099713825, 3.493902212696578, 3.2780138322635404, 2.440472146821701, 3.9237587739289017, 3.3277753418226044, 3.7538597371335043, 2.432103897151185, 3.412933150162911, 3.7230880784667506, 3.3694480382231724, 4.917010546939185, 4.47875561600803, 2.448911015467566, 4.968303841326735, 2.915530546729061, 3.869691552658626, 3.493902212696578, 3.9809171877688505, 3.6786363158959166, 3.5952547069568657, 4.02092252238255, 3.9614991019117487, 3.8183982582710754, 4.062595218783118, 3.905409635260705, 3.7230880784667506, 3.518293665820737, 4.693866995624976, 4.357394759003762, 3.2683519213518033, 4.386382295877015, 3.506023573228923, 4.82170036713486, 3.15056888569542, 3.6500629434518608, 3.412933150162911, 4.47875561600803, 4.917010546939185, 4.329223882037066, 4.301824907848951, 4.151542704799613, 3.5432949680261547, 3.185355001780836, 3.0223936922714225, 5.07952947643696, 1.805719932750922, 2.2602536402245255, 3.6642475784438173, 4.357394759003762, 2.753687521278647, 4.416235259026696, 2.5514506547837508, 4.041541809585285, 3.287770007208905, 2.818992619686414, 3.905409635260705, 4.357394759003762, 3.23991398603127, 4.128553186574915, 4.654646282471694, 3.869691552658626, 3.8183982582710754, 2.971100397883872, 3.70805020110221, 3.9614991019117487, 3.8522998099467567, 3.8522998099467567, 4.329223882037066, 3.2683519213518033, 2.037812089641146, 3.15056888569542, 5.61015772749913, 2.6397432619294294, 4.24918117436353, 2.2394195533216834, 3.5560339938035845, 1.5636038291133783, 4.2238633663792395, 3.835205376587457, 3.801868956319865, 2.292341954776026, 2.882304899100741, 3.9424509069410543, 3.801868956319865, 1.0447684115228837, 2.908796514547717, 4.616905954488847, 3.869691552658626, 3.4583955242396685, 3.9809171877688505, 3.6642475784438173, 3.7856084354480846, 3.7538597371335043, 3.7538597371335043, 4.27515666076679, 1.2268818734248168, 3.3694480382231724, 1.8701099868107947, 3.9424509069410543, 2.2743881511594304, 3.7538597371335043, 4.199170753788868, 1.670519555038011, 4.301824907848951, 3.518293665820737, 3.9809171877688505, 2.0462747635598797, 3.6500629434518608, 2.971100397883872, 1.9621002679054493, 2.166539629953023, 4.128553186574915, 3.052930416131504, 4.82170036713486, 4.386382295877015, 4.329223882037066, 2.765248343679723, 3.9809171877688505, 3.7538597371335043, 4.27515666076679, 3.7856084354480846, 3.7538597371335043, 4.580538310317973, 4.128553186574915, 3.9809171877688505, 4.357394759003762, 2.24978234035723, 4.654646282471694, 3.8183982582710754, 4.24918117436353, 3.869691552658626, 3.6086777272890065, 4.000719815065031, 3.738355550597539, 3.9809171877688505, 4.5454469905067025, 2.963982930115008, 3.7538597371335043, 5.07952947643696, 3.424106450761036, 4.084101424004081, 4.24918117436353, 3.869691552658626, 3.2976223036519166, 3.887391129758027, 4.44700691769345, 3.835205376587457, 3.622283379344785, 4.041541809585285, 4.2238633663792395, 4.175073202209807, 3.3176229703585864, 4.128553186574915, 4.02092252238255, 3.3909542434441358, 4.27515666076679, 4.151542704799613, 3.7696080941016437, 3.8522998099467567, 3.7696080941016437, 3.70805020110221, 4.084101424004081, 4.106080330722856, 4.27515666076679, 3.7230880784667506, 5.427836170705175, 3.401883313976326, 3.4468347018385925, 3.6500629434518608, 4.24918117436353, 4.02092252238255, 4.175073202209807, 3.636076701477121, 4.02092252238255, 4.106080330722856, 3.9237587739289017, 4.386382295877015, 3.7538597371335043, 3.0000879347571243, 3.9424509069410543, 3.1420581960275116, 3.887391129758027, 4.175073202209807, 3.887391129758027, 3.835205376587457, 3.9614991019117487, 3.8183982582710754, 4.128553186574915, 3.3483946290253397, 3.9809171877688505, 4.084101424004081, 3.5307161858192946, 3.3483946290253397, 3.8522998099467567, 3.424106450761036, 3.6786363158959166, 3.493902212696578, 4.106080330722856, 4.151542704799613, 4.44700691769345, 4.175073202209807, 3.9424509069410543, 4.2238633663792395, 3.4700915640028596, 3.9424509069410543, 4.062595218783118, 3.412933150162911, 4.357394759003762, 4.062595218783118, 4.106080330722856, 3.506023573228923, 3.9424509069410543, 3.5432949680261547, 4.416235259026696, 3.2306115933689563, 4.301824907848951, 3.8183982582710754, 3.869691552658626, 4.000719815065031, 3.5952547069568657, 5.07952947643696, 4.062595218783118, 4.199170753788868, 3.3909542434441358, 3.835205376587457, 4.386382295877015, 4.175073202209807, 1.7750157664069421, 3.869691552658626, 4.44700691769345, 2.8757902180795467, 4.917010546939185, 3.7230880784667506, 3.0375454972920246, 3.801868956319865, 3.0764609135416983, 4.128553186574915, 4.511545438831021, 4.041541809585285, 4.357394759003762, 4.44700691769345, 4.47875561600803, 4.27515666076679, 3.0452083700375936, 4.175073202209807, 4.02092252238255, 4.000719815065031, 2.686996146779975, 4.199170753788868, 3.4468347018385925, 4.2238633663792395, 3.801868956319865, 3.7538597371335043, 3.3277753418226044, 4.02092252238255, 3.3588659288926355, 3.506023573228923, 2.6923869954148514, 3.23991398603127, 4.199170753788868, 3.0375454972920246, 5.022371062597012, 3.7696080941016437, 2.5145801189754233, 3.43540600601497, 3.9809171877688505, 4.693866995624976, 3.6500629434518608, 3.9237587739289017, 3.5952547069568657, 2.66571874833269, 3.9809171877688505, 4.47875561600803, 4.199170753788868, 4.301824907848951, 4.128553186574915, 3.568937398639492, 3.1942439491980816, 2.1633498345849227, 4.128553186574915, 4.301824907848951, 3.6932351153170693, 4.511545438831021, 1.9965407578857408, 4.041541809585285, 3.412933150162911, 3.835205376587457, 4.175073202209807, 4.151542704799613, 3.6500629434518608, 4.82170036713486, 3.4583955242396685, 3.835205376587457, 4.106080330722856, 4.199170753788868, 4.27515666076679, 4.02092252238255, 3.801868956319865, 4.199170753788868, 4.199170753788868, 4.084101424004081, 4.151542704799613, 3.887391129758027, 3.2587824703356527, 4.062595218783118, 3.4583955242396685, 3.9237587739289017, 3.582009480206845, 4.27515666076679, 2.599536841451389, 4.416235259026696, 4.301824907848951, 4.301824907848951, 3.636076701477121, 4.2238633663792395, 3.887391129758027, 4.199170753788868, 3.738355550597539, 2.440472146821701, 4.301824907848951, 3.9237587739289017, 4.693866995624976, 3.21226245470076, 3.506023573228923, 4.386382295877015, 4.199170753788868, 3.1765443720986806, 3.7538597371335043, 2.730959270201091, 3.582009480206845, 3.5560339938035845, 4.5454469905067025, 4.693866995624976, 3.9424509069410543, 4.301824907848951, 4.106080330722856, 3.622283379344785, 4.47875561600803, 4.084101424004081, 3.70805020110221, 4.5454469905067025, 3.6932351153170693, 2.004659882324245, 3.835205376587457, 5.07952947643696, 1.2860250712441514, 3.6086777272890065, 1.031331516850641, 1.8917194711436498, 2.295971722826605, 3.7856084354480846, 2.676300857663227, 1.9543181274633943, 4.128553186574915, 2.4531573063490173, 1.799060640660945, 3.7230880784667506, 3.5560339938035845, 2.963982930115008, 3.203212619180842, 1.4894958569596564, 2.634628161262659, 3.2976223036519166, 3.5307161858192946, 2.759451225995397, 2.882304899100741, 4.24918117436353, 2.2325702114761086, 3.2976223036519166, 3.9614991019117487, 1.030305349495329, 6.814130531825066, 3.70805020110221, 3.8183982582710754, 2.8757902180795467, 3.887391129758027, 2.971100397883872, 3.2976223036519166, 4.654646282471694, 4.44700691769345, 3.3801433273399204, 4.416235259026696, 4.616905954488847, 3.636076701477121, 4.175073202209807, 3.905409635260705, 3.887391129758027, 4.199170753788868, 4.2238633663792395, 4.175073202209807, 3.9809171877688505, 3.738355550597539, 3.7230880784667506, 4.062595218783118, 3.869691552658626, 3.9614991019117487, 3.8183982582710754, 2.2851217068025393, 4.175073202209807, 3.0844290831908747, 6.303304908059076, 2.818992619686414, 3.8522998099467567, 3.568937398639492, 3.636076701477121, 2.794749008076421, 1.8868768466678618, 2.2815310386718104, 2.599536841451389, 2.8067973465925955, 4.616905954488847, 3.6642475784438173, 2.985489135335971, 4.968303841326735, 4.24918117436353, 4.580538310317973, 3.9809171877688505, 2.5467668054713246, 4.151542704799613, 3.9424509069410543, 4.106080330722856, 4.062595218783118, 4.82170036713486, 4.868220382769753, 4.511545438831021, 3.029940897906805, 3.9237587739289017, 3.2306115933689563, 4.5454469905067025, 3.9424509069410543, 1.4927478923460338, 4.654646282471694, 4.128553186574915, 2.6978070628841904, 2.1475517177083314, 4.301824907848951, 4.041541809585285, 3.116952274896435, 3.6500629434518608, 2.411484609948449, 3.636076701477121, 1.87726138796842, 3.9237587739289017, 3.9237587739289017, 2.1891577185407955, 2.1258454391264685, 2.6397432619294294, 3.3801433273399204, 1.6531613564282532, 2.3912819026309293, 4.2238633663792395, 1.9262908152087386, 3.506023573228923, 3.887391129758027, 3.3694480382231724, 1.7203803310183041, 3.518293665820737, 4.062595218783118, 1.29266961396282, 3.3277753418226044, 3.203212619180842, 4.27515666076679, 3.3801433273399204, 2.8128763926689775, 4.416235259026696, 3.6786363158959166, 4.062595218783118, 2.411484609948449, 3.7856084354480846, 1.8701099868107947, 2.92913619878484, 4.301824907848951, 4.24918117436353, 2.2602536402245255, 3.7538597371335043, 2.2190106816904764, 3.4468347018385925, 4.000719815065031, 2.1319993047008468, 4.128553186574915, 2.730959270201091, 3.905409635260705]}